CHANGELOG.rst
LICENSE
MANIFEST.in
README.rst
setup.cfg
setup.py
annotypes/__init__.py
annotypes/_anno.py
annotypes/_array.py
annotypes/_calltypes.py
annotypes/_compat.py
annotypes/_frozen_dict.py
annotypes/_serializable.py
annotypes/_stackinfo.py
annotypes/_typing.py
annotypes/version.py
annotypes.egg-info/PKG-INFO
annotypes.egg-info/SOURCES.txt
annotypes.egg-info/dependency_links.txt
annotypes.egg-info/not-zip-safe
annotypes.egg-info/top_level.txt
annotypes/py2_examples/__init__.py
annotypes/py2_examples/composition.py
annotypes/py2_examples/enumtaker.py
annotypes/py2_examples/manyargs.py
annotypes/py2_examples/mapping.py
annotypes/py2_examples/reusecls.py
annotypes/py2_examples/simple.py
annotypes/py2_examples/table.py
annotypes/py3_examples/__init__.py
annotypes/py3_examples/composition.py
annotypes/py3_examples/enumtaker.py
annotypes/py3_examples/manyargs.py
annotypes/py3_examples/mapping.py
annotypes/py3_examples/reusecls.py
annotypes/py3_examples/simple.py
annotypes/py3_examples/table.py
annotypes/sphinxext/__init__.py
annotypes/sphinxext/call_types.py