Metadata-Version: 1.1
Name: annotypes
Version: 0.21
Summary: Annotating type hints and comments with extra metatdata
Home-page: https://github.com/dls-controls/annotypes
Author: Tom Cobb
Author-email: tom.cobb@diamond.ac.uk
License: APACHE
Platform: UNKNOWN
Classifier: Development Status :: 3 - Alpha
Classifier: Intended Audience :: Developers
Classifier: Natural Language :: English
Classifier: Operating System :: POSIX :: Linux
Classifier: Programming Language :: Python :: 2.7
Classifier: Programming Language :: Python :: 3.4
Classifier: Programming Language :: Python :: 3.5
Classifier: Programming Language :: Python :: 3.6
